customllib/__init__.py
customllib/supervised/__init__.py
customllib/supervised/classification/__init__.py
customllib/supervised/classification/logistic_regression.py
customllib/supervised/regression/__init__.py
customllib/supervised/regression/linear_regression.py
customllib/unsupervised/__init__.py
customllib/unsupervised/clustering/__init__.py
customllib/unsupervised/clustering/kmeans_clustering.py
customllib/utils/__init__.py
customllib/utils/feature_scaling.py
customllib-0.0.3.dist-info/METADATA
customllib-0.0.3.dist-info/WHEEL
customllib-0.0.3.dist-info/licenses/LICENSE
customllib-0.0.3.dist-info/RECORD
